rom_manager/__init__.py
rom_manager/game_codes.py
rom_manager/rom_manager.py
rom_manager/version.py
rom_manager-0.0.26.dist-info/LICENSE
rom_manager-0.0.26.dist-info/METADATA
rom_manager-0.0.26.dist-info/WHEEL
rom_manager-0.0.26.dist-info/entry_points.txt
rom_manager-0.0.26.dist-info/top_level.txt
rom_manager-0.0.26.dist-info/RECORD
