Metadata-Version: 2.1
Name: rom-manager
Version: 0.0.26
Summary: Synchronize your subtitle files by shifting the subtitle time (+/-)
Home-page: https://github.com/Knuckles-Team/rom-manager
Author: Audel Rouhi
Author-email: knucklessg1@gmail.com
License: MIT
Platform: UNKNOWN
Classifier: Development Status :: 5 - Production/Stable
Classifier: License :: Public Domain
Classifier: Environment :: Console
Classifier: Operating System :: POSIX :: Linux
Classifier: Programming Language :: Python :: 3.8
Classifier: Programming Language :: Python :: 3.9
Classifier: Programming Language :: Python :: 3.10
Classifier: Programming Language :: Python :: 3.11
Classifier: Programming Language :: Python :: 3.12
License-File: LICENSE
Requires-Dist: patool (>=2.1.1)
